README.md
main.py
setup.py
deepl_translator_selenium.egg-info/PKG-INFO
deepl_translator_selenium.egg-info/SOURCES.txt
deepl_translator_selenium.egg-info/dependency_links.txt
deepl_translator_selenium.egg-info/entry_points.txt
deepl_translator_selenium.egg-info/requires.txt
deepl_translator_selenium.egg-info/top_level.txt
subtitle/helper.py
translator/deepl.py